topsis_lavanya_102313066/__init__.py
topsis_lavanya_102313066/cli.py
topsis_lavanya_102313066/topsis.py
topsis_lavanya_102313066-1.0.1.dist-info/licenses/LICENSE
topsis_lavanya_102313066-1.0.1.dist-info/METADATA
topsis_lavanya_102313066-1.0.1.dist-info/WHEEL
topsis_lavanya_102313066-1.0.1.dist-info/entry_points.txt
topsis_lavanya_102313066-1.0.1.dist-info/top_level.txt
topsis_lavanya_102313066-1.0.1.dist-info/RECORD
