Metadata-Version: 2.4
Name: topsis-lavanya-102313066
Version: 1.0.1
Summary: TOPSIS (Technique for Order Preference by Similarity to Ideal Solution) implementation for multi-criteria decision making
Home-page: https://github.com/lavanya-garg/topsis-lavanya-102313066
Author: Lavanya Garg
Author-email: lgarg_be23@thapar.edu
Project-URL: Bug Reports, https://github.com/lavanya-garg/topsis-lavanya-102313066/issues
Project-URL: Documentation, https://github.com/lavanya-garg/topsis-lavanya-102313066
Project-URL: Source Code, https://github.com/lavanya-garg/topsis-lavanya-102313066
Keywords: topsis mcdm decision-making multi-criteria
Classifier: Development Status :: 4 - Beta
Classifier: Intended Audience :: Developers
Classifier: Intended Audience :: Science/Research
Classifier: Topic :: Scientific/Engineering
Classifier: Topic :: Scientific/Engineering :: Information Analysis
Classifier: Topic :: Office/Business
Classifier: License :: OSI Approved :: MIT License
Classifier: Programming Language :: Python :: 3
Classifier: Programming Language :: Python :: 3.7
Classifier: Programming Language :: Python :: 3.8
Classifier: Programming Language :: Python :: 3.9
Classifier: Programming Language :: Python :: 3.10
Classifier: Programming Language :: Python :: 3.11
Classifier: Programming Language :: Python :: 3.12
Classifier: Operating System :: OS Independent
Requires-Python: >=3.7
License-File: LICENSE
Requires-Dist: pandas>=1.0.0
Requires-Dist: numpy>=1.18.0
Dynamic: author
Dynamic: author-email
Dynamic: classifier
Dynamic: description
Dynamic: description-content-type
Dynamic: home-page
Dynamic: keywords
Dynamic: license-file
Dynamic: project-url
Dynamic: requires-dist
Dynamic: requires-python
Dynamic: summary
